reactflow_css/__init__.py
reactflow_css/bootstrap/Configuration.py
reactflow_css/bootstrap/__init__.py
reactflow_css/bootstrap/exceptions.py
reactflow_css/bootstrap/generate.py
reactflow_css/modules/bootstrap/css/bootstrap-grid.css
reactflow_css/modules/bootstrap/css/bootstrap-grid.css.map
reactflow_css/modules/bootstrap/css/bootstrap-grid.min.css
reactflow_css/modules/bootstrap/css/bootstrap-grid.min.css.map
reactflow_css/modules/bootstrap/css/bootstrap-grid.rtl.css
reactflow_css/modules/bootstrap/css/bootstrap-grid.rtl.css.map
reactflow_css/modules/bootstrap/css/bootstrap-grid.rtl.min.css
reactflow_css/modules/bootstrap/css/bootstrap-grid.rtl.min.css.map
reactflow_css/modules/bootstrap/css/bootstrap-reboot.css
reactflow_css/modules/bootstrap/css/bootstrap-reboot.css.map
reactflow_css/modules/bootstrap/css/bootstrap-reboot.min.css
reactflow_css/modules/bootstrap/css/bootstrap-reboot.min.css.map
reactflow_css/modules/bootstrap/css/bootstrap-reboot.rtl.css
reactflow_css/modules/bootstrap/css/bootstrap-reboot.rtl.css.map
reactflow_css/modules/bootstrap/css/bootstrap-reboot.rtl.min.css
reactflow_css/modules/bootstrap/css/bootstrap-reboot.rtl.min.css.map
reactflow_css/modules/bootstrap/css/bootstrap-utilities.css
reactflow_css/modules/bootstrap/css/bootstrap-utilities.css.map
reactflow_css/modules/bootstrap/css/bootstrap-utilities.min.css
reactflow_css/modules/bootstrap/css/bootstrap-utilities.min.css.map
reactflow_css/modules/bootstrap/css/bootstrap-utilities.rtl.css
reactflow_css/modules/bootstrap/css/bootstrap-utilities.rtl.css.map
reactflow_css/modules/bootstrap/css/bootstrap-utilities.rtl.min.css
reactflow_css/modules/bootstrap/css/bootstrap-utilities.rtl.min.css.map
reactflow_css/modules/bootstrap/css/bootstrap.css
reactflow_css/modules/bootstrap/css/bootstrap.css.map
reactflow_css/modules/bootstrap/css/bootstrap.min.css
reactflow_css/modules/bootstrap/css/bootstrap.min.css.map
reactflow_css/modules/bootstrap/css/bootstrap.rtl.css
reactflow_css-1.0.6.dist-info/licenses/LICENSE
reactflow_css-1.0.6.dist-info/METADATA
reactflow_css-1.0.6.dist-info/WHEEL
reactflow_css-1.0.6.dist-info/top_level.txt
reactflow_css-1.0.6.dist-info/RECORD
