Metadata-Version: 2.4
Name: ReactFlow_CSS
Version: 1.0.6
Summary: This is pkg to load styling (tailwindcss and bootstrap) for reactpy, backend reactpy or other html files
Home-page: https://github.com/Elang-elang/tailwind-py
Author: Elang Muhammad
Author-email: elangmuhammad888@gmail.com
Keywords: tailwind,tailwindcss,style,reactpy,tailwind-py,bootstrap,bootstrap-py,reactflow,css,reactflow-css,reactflow_css
Classifier: Programming Language :: Python :: 3
Classifier: Programming Language :: Python :: 3.8
Classifier: Programming Language :: Python :: 3.9
Classifier: Programming Language :: Python :: 3.10
Classifier: Programming Language :: Python :: 3.11
Classifier: Programming Language :: Python :: 3.12
Classifier: Programming Language :: JavaScript
Classifier: License :: OSI Approved :: MIT License
Classifier: Operating System :: OS Independent
Classifier: Topic :: Software Development :: Libraries :: Python Modules
Classifier: Topic :: Internet :: WWW/HTTP :: Dynamic Content
Classifier: Topic :: Text Processing :: Markup :: HTML
Classifier: Intended Audience :: Developers
Classifier: Development Status :: 4 - Beta
Classifier: Environment :: Web Environment
Requires-Python: >=3.8
License-File: LICENSE
Dynamic: author
Dynamic: author-email
Dynamic: classifier
Dynamic: description
Dynamic: description-content-type
Dynamic: home-page
Dynamic: keywords
Dynamic: license-file
Dynamic: requires-python
Dynamic: summary
